{
  "compiler-version": "0.32.102",
  "language-version": "0.24.101",
  "runtime-version": "0.17.102",
  "circuits": [
    {
      "name": "emitMisc",
      "pure": false,
      "proof": true,
      "arguments": [
        {
          "name": "name",
          "type": {
            "type-name": "Bytes",
            "length": 32
          }
        },
        {
          "name": "payload",
          "type": {
            "type-name": "Bytes",
            "length": 256
          }
        }
      ],
      "result-type": {
        "type-name": "Tuple",
        "types": [
        ]
      }
    },
    {
      "name": "emitShieldedSpend",
      "pure": false,
      "proof": true,
      "arguments": [
        {
          "name": "nullifier",
          "type": {
            "type-name": "Bytes",
            "length": 32
          }
        }
      ],
      "result-type": {
        "type-name": "Tuple",
        "types": [
        ]
      }
    },
    {
      "name": "emitShieldedReceive",
      "pure": false,
      "proof": true,
      "arguments": [
        {
          "name": "commitment",
          "type": {
            "type-name": "Bytes",
            "length": 32
          }
        }
      ],
      "result-type": {
        "type-name": "Tuple",
        "types": [
        ]
      }
    },
    {
      "name": "emitShieldedMint",
      "pure": false,
      "proof": true,
      "arguments": [
        {
          "name": "commitment",
          "type": {
            "type-name": "Bytes",
            "length": 32
          }
        }
      ],
      "result-type": {
        "type-name": "Tuple",
        "types": [
        ]
      }
    },
    {
      "name": "emitShieldedBurn",
      "pure": false,
      "proof": true,
      "arguments": [
        {
          "name": "nullifier",
          "type": {
            "type-name": "Bytes",
            "length": 32
          }
        }
      ],
      "result-type": {
        "type-name": "Tuple",
        "types": [
        ]
      }
    },
    {
      "name": "emitUnshieldedSpend",
      "pure": false,
      "proof": true,
      "arguments": [
        {
          "name": "tokenType",
          "type": {
            "type-name": "Bytes",
            "length": 32
          }
        },
        {
          "name": "amount",
          "type": {
            "type-name": "Uint",
            "maxval": 340282366920938463463374607431768211455
          }
        }
      ],
      "result-type": {
        "type-name": "Tuple",
        "types": [
        ]
      }
    },
    {
      "name": "emitUnshieldedReceive",
      "pure": false,
      "proof": true,
      "arguments": [
        {
          "name": "tokenType",
          "type": {
            "type-name": "Bytes",
            "length": 32
          }
        },
        {
          "name": "amount",
          "type": {
            "type-name": "Uint",
            "maxval": 340282366920938463463374607431768211455
          }
        }
      ],
      "result-type": {
        "type-name": "Tuple",
        "types": [
        ]
      }
    },
    {
      "name": "emitUnshieldedMint",
      "pure": false,
      "proof": true,
      "arguments": [
        {
          "name": "tokenType",
          "type": {
            "type-name": "Bytes",
            "length": 32
          }
        },
        {
          "name": "amount",
          "type": {
            "type-name": "Uint",
            "maxval": 340282366920938463463374607431768211455
          }
        }
      ],
      "result-type": {
        "type-name": "Tuple",
        "types": [
        ]
      }
    },
    {
      "name": "emitUnshieldedBurn",
      "pure": false,
      "proof": true,
      "arguments": [
        {
          "name": "tokenType",
          "type": {
            "type-name": "Bytes",
            "length": 32
          }
        },
        {
          "name": "amount",
          "type": {
            "type-name": "Uint",
            "maxval": 340282366920938463463374607431768211455
          }
        }
      ],
      "result-type": {
        "type-name": "Tuple",
        "types": [
        ]
      }
    },
    {
      "name": "emitLifecycle",
      "pure": false,
      "proof": true,
      "arguments": [
      ],
      "result-type": {
        "type-name": "Tuple",
        "types": [
        ]
      }
    }
  ],
  "witnesses": [
  ],
  "contracts": [
  ],
  "ledger": [
  ]
}
